[
    {
        "name": "Oscar",
        "lastname": "Islas",
        "email": "oislasreyes@gmail.com",
        "password": "oscar1234"
    }, {
        "name": "Oscar",
        "lastname": "Islas",
        "email": "oislasreyes@gmail.com",
        "password": "oscar1234"
    }, {
        "name": "Luis",
        "lastname": "Hernandez",
        "email": "luis06@gmail.com",
        "password": "1234567"
    }, {
        "name": "Luis",
        "lastname": "Hernandez",
        "email": "luis06@gmail.com",
        "password": "1234567"
    }, {
        "name": "Luis",
        "lastname": "Hernandez",
        "email": "luis06@gmail.com",
        "password": "1234567"
    }, {
        "name": "Oscar",
        "lastname": "Islas",
        "email": "oislasreyes@gmail.com",
        "password": "oscar1234"
    }, {
        "name": "Oscar",
        "lastname": "Islas",
        "email": "oislasreyes@gmail.com",
        "password": "oscar1234"
    }, {
        "name": "Oscar",
        "lastname": "Hernandez",
        "email": "oscar.islas@gmail.com",
        "password": "oscar1234"
    }, {
        "name": "Oscar",
        "lastname": "Hernandez",
        "email": "oscar.islas@gmail.com",
        "password": "oscar1234"
    }
]